flatten_utils/__init__.py
flatten_utils/cli.py
flatten_utils/core.py
flatten_utils-0.1.3.dist-info/licenses/LICENSE
tests/__init__.py
tests/test_cli.py
tests/test_core.py
flatten_utils-0.1.3.dist-info/METADATA
flatten_utils-0.1.3.dist-info/WHEEL
flatten_utils-0.1.3.dist-info/entry_points.txt
flatten_utils-0.1.3.dist-info/top_level.txt
flatten_utils-0.1.3.dist-info/RECORD
