Metadata-Version: 2.4
Name: flatten-utils
Version: 0.1.3
Summary: CLi + module to deeply flatten nested structures like a pro
Author: StarCoderSC
License: MIT
Classifier: Programming Language :: Python :: 3
Classifier: Operating System :: OS Independent
Requires-Python: >=3.7
License-File: LICENSE
Dynamic: author
Dynamic: classifier
Dynamic: description
Dynamic: description-content-type
Dynamic: license
Dynamic: license-file
Dynamic: requires-python
Dynamic: summary
